pytest_deduplicate.py
pytest_deduplicate-0.1.6.dist-info/LICENSE
pytest_deduplicate-0.1.6.dist-info/METADATA
pytest_deduplicate-0.1.6.dist-info/WHEEL
pytest_deduplicate-0.1.6.dist-info/entry_points.txt
pytest_deduplicate-0.1.6.dist-info/top_level.txt
pytest_deduplicate-0.1.6.dist-info/RECORD
