Metadata-Version: 2.1
Name: pytest-deduplicate
Version: 0.1.6
Summary: Identifies duplicate unit tests
Author-email: xor2003 <xor2003@gmx.com>
License: GPL
Project-URL: Homepage, https://github.com/xor2003/pytest_deduplicate
Keywords: duplicate test detection,test optimization,test efficiency
Classifier: Development Status :: 4 - Beta
Classifier: Intended Audience :: Developers
Classifier: License :: OSI Approved :: GNU General Public License v3 or later (GPLv3+)
Classifier: Programming Language :: Python :: 3
Classifier: Programming Language :: Python :: 3.10
Classifier: Programming Language :: Python :: 3.11
Classifier: Programming Language :: Python :: 3.8
Classifier: Programming Language :: Python :: 3.9
Classifier: Topic :: Software Development :: Testing :: Unit
Classifier: Operating System :: OS Independent
Classifier: Topic :: Software Development :: Quality Assurance
Requires-Python: >=3.8
License-File: LICENSE
Requires-Dist: pytest
Requires-Dist: coverage
